oracowl/__init__.py
oracowl/dso_db.py
oracowl/engine.py
oracowl-1.0.1.dist-info/LICENSE.txt
oracowl-1.0.1.dist-info/METADATA
oracowl-1.0.1.dist-info/WHEEL
oracowl-1.0.1.dist-info/top_level.txt
oracowl-1.0.1.dist-info/RECORD
