Metadata-Version: 2.1
Name: oracowl
Version: 1.0.1
Summary: A simple package based on PyEphem to calculate deep sky objects and planetary data, such as rise, set, transit, and altitude along with other objects information like magnitude, size, and distance and so on.
Home-page: https://oracowl.io
Author: Marco Rapino
Author-email: aktasway@gmail.com
License: MIT
Project-URL: Documentation, https://oracowl.io/docs/index.html
Project-URL: Source, https://github.com/aktasway-it/oracowl-py/
Platform: any
Classifier: Development Status :: 4 - Beta
Classifier: Programming Language :: Python
Requires-Python: >=3.8
License-File: LICENSE.txt
Requires-Dist: pyephem
Requires-Dist: timezonefinder[pytz]
